LICENSE
MANIFEST.in
README.md
ReleaseNotes
setup.py
pacutils/__init__.py
pacutils/cancel.py
pacutils/cleanup.py
pacutils/common.py
pacutils/discovery.py
pacutils/information.py
pacutils/pac_op.py
pacutils/program.py
pacutils/progress.py
pacutils/setup.py
pacutils.egg-info/PKG-INFO
pacutils.egg-info/SOURCES.txt
pacutils.egg-info/dependency_links.txt
pacutils.egg-info/entry_points.txt
pacutils.egg-info/requires.txt
pacutils.egg-info/top_level.txt